{"id":24361,"date":"2015-02-23T13:53:07","date_gmt":"2015-02-23T06:53:07","guid":{"rendered":"https:\/\/konsultasisyariah-com.s1708lqs-liquidwebsites.com\/?p=24361"},"modified":"2021-06-21T17:50:29","modified_gmt":"2021-06-21T10:50:29","slug":"istri-harus-tinggal-bersama-suami","status":"publish","type":"post","link":"https:\/\/konsultasisyariah.com\/24361-istri-harus-tinggal-bersama-suami.html","title":{"rendered":"Istri Harus Tinggal Bersama Suami?"},"content":{"rendered":"<p><iframe width=\"100%\" height=\"166\" scrolling=\"no\" frameborder=\"no\" allow=\"autoplay\" src=\"https:\/\/w.soundcloud.com\/player\/?url=https%3A\/\/api.soundcloud.com\/tracks\/1072815577&#038;color=d5265f&#038;hide_related=true&#038;show_artwork=false&#038;show_comments=false&#038;show_teaser=false&#038;show_user=false\"><\/iframe><\/p>\n<h2><strong>Haruskah Istri Tinggal Bersama Suami?<\/strong><\/h2>\n<p><em>Saya seorang istri tinggal dijkrt ini sama anak 2 dan cucu . tetapi suami ndak betah disini , mau nya tinggal dkmpung . alasan nya sakit 2 disini .sisuami mintak saya tnggal dikapung . sementara tanggung jawap dan kewajiban nya sebagai suami telah dipikul oleh anak 2 nya .kl mengenai usia belum terlalu tua 68 tahun masih kuat .pertnyaan saya ,, apakah bedosa saya tak mau ikut menemaninya dikampung<\/em><\/p>\n<p><em>Dari Elis S<\/em><\/p>\n<p><strong>Jawab:<\/strong><\/p>\n<p><em>Bismillah was shalatu was salamu \u2018ala Rasulillah, amma ba\u2019du,<\/em><\/p>\n<p>Diantara tujuan Allah syariatkan umat manusia menikah adalah agar mereka bisa hidup bersama dalam ketenangan. Allah berfirman,<\/p>\n<p class=\"arab\">\u0648\u064e\u0645\u0650\u0646\u0652 \u0622\u064e\u064a\u064e\u0627\u062a\u0650\u0647\u0650 \u0623\u064e\u0646\u0652 \u062e\u064e\u0644\u064e\u0642\u064e \u0644\u064e\u0643\u064f\u0645\u0652 \u0645\u0650\u0646\u0652 \u0623\u064e\u0646\u0652\u0641\u064f\u0633\u0650\u0643\u064f\u0645\u0652 \u0623\u064e\u0632\u0652\u0648\u064e\u0627\u062c\u064b\u0627 \u0644\u0650\u062a\u064e\u0633\u0652\u0643\u064f\u0646\u064f\u0648\u0627 \u0625\u0650\u0644\u064e\u064a\u0652\u0647\u064e\u0627 \u0648\u064e\u062c\u064e\u0639\u064e\u0644\u064e \u0628\u064e\u064a\u0652\u0646\u064e\u0643\u064f\u0645\u0652 \u0645\u064e\u0648\u064e\u062f\u0651\u064e\u0629\u064b \u0648\u064e\u0631\u064e\u062d\u0652\u0645\u064e\u0629\u064b<\/p>\n<p><em>Di antara tanda-tanda kekuasaan-Nya ialah Dia menciptakan untukmu isteri-isteri dari jenismu sendiri, supaya kamu cenderung dan merasa tenteram kepadanya, dan dijadikan-Nya diantaramu rasa kasih dan sayang.<\/em> (QS. Rum: 21).<\/p>\n<p>Karena itu, disyariatkan agar suami istri selalu tinggal bersama.<\/p>\n<p>Dan aturan semacam ini tidak hanya berlaku bagi umat Muhammad Shallallahu &#8216;alaihi wa sallam. Tapi juga menjadi ajaran nabi masa silam. Diantaranya nabi Musa \u2018alaihis shalatu was salam.<\/p>\n<p>Dalam al-Quran, tepatnya di surat al-Qashas ayat 23 hingga 30, Allah menceritakan keluarga Musa. Setelah Musa menuju Madyan, beliau dinikahkan dengan putri salah satu orang soleh di kampung itu, dengan mahar, bekerja menjadi penggembala kambing selama 10 tahun.<\/p>\n<p>Setelah Musa menyelesaikan tugasnya, beliau kembali ke Mesir untuk misi membebaskan Bani Israil yang dijajah Firaun. Dalam pengalan kisah, Musa kembali ke Mesir bersama istrinya,<\/p>\n<p class=\"arab\">\u0641\u064e\u0644\u064e\u0645\u0651\u064e\u0627 \u0642\u064e\u0636\u064e\u0649 \u0645\u064f\u0648\u0633\u064e\u0649 \u0627\u0644\u0652\u0623\u064e\u062c\u064e\u0644\u064e \u0648\u064e\u0633\u064e\u0627\u0631\u064e \u0628\u0650\u0623\u064e\u0647\u0652\u0644\u0650\u0647\u0650<\/p>\n<p>\u201cTatkala Musa telah menyelesaikan waktu yang ditentukan dan dia berangkat dengan keluarganya..\u201d (QS. al-Qashas: 29)<\/p>\n<p>Ketika menafsirkan ayat ini, al-Qurthubi menuliskan,<\/p>\n<p class=\"arab\">\u0641\u064a\u0647 \u062f\u0644\u064a\u0644 \u0639\u0644\u0649 \u0623\u0646 \u0627\u0644\u0631\u062c\u0644 \u064a\u0630\u0647\u0628 \u0628\u0623\u0647\u0644\u0647 \u062d\u064a\u062b \u0634\u0627\u0621 \u0644\u0645\u0627 \u0644\u0647 \u0639\u0644\u064a\u0647\u0627 \u0645\u0646 \u0641\u0636\u0644 \u0627\u0644\u0642\u0648\u0627\u0645\u0629<\/p>\n<p>Dalam ayat ini terdapat dalil bahwa seorang suami merantau dengan membawa istrinya sesuai yang diinginkan suaminya. Suami diunggulkan karena posisinya sebagai pemimpin keluarganya. (Tafsir al-Qurthubi, 13\/281).<\/p>\n<p>Hanya saja, islam melarang keras, para suami menempatkan istri di tempat yang sangat tidak nyaman, dengan maksud untuk mendzalimi istrinya. Sebagaimana islam juga melarang suami tidak memberikan nafkah kepada istrinya karena ingin mendzalimi istrinya.<\/p>\n<p>Allah berfirman,<\/p>\n<p class=\"arab\">\u0623\u064e\u0633\u0652\u0643\u0650\u0646\u064f\u0648\u0647\u064f\u0646\u0651\u064e \u0645\u0650\u0646\u0652 \u062d\u064e\u064a\u0652\u062b\u064f \u0633\u064e\u0643\u064e\u0646\u0652\u062a\u064f\u0645\u0652 \u0645\u0650\u0646\u0652 \u0648\u064f\u062c\u0652\u062f\u0650\u0643\u064f\u0645\u0652 \u0648\u064e\u0644\u064e\u0627 \u062a\u064f\u0636\u064e\u0627\u0631\u0651\u064f\u0648\u0647\u064f\u0646\u0651\u064e \u0644\u0650\u062a\u064f\u0636\u064e\u064a\u0651\u0650\u0642\u064f\u0648\u0627 \u0639\u064e\u0644\u064e\u064a\u0652\u0647\u0650\u0646\u0651\u064e<\/p>\n<p><em>\u201cTempatkanlah mereka (para isteri) di mana kamu bertempat tinggal menurut kemampuanmu dan janganlah kamu menyusahkan mereka untuk menyempitkan (hati) mereka.\u201d<\/em> (QS. at-Thalaq: 6)<\/p>\n<p>Yang dimaksud, \u2018<em>janganlah kamu menyusahkan mereka<\/em>\u2019 adalah menyusahkan istri dalam masalah tempat tinggal dan nafkah. Disebabkan suami hendak mendzalimi istrinya.<\/p>\n<p>Karena itu, semangat yang dibangun adalah tinggal bersama untuk hidup bersama. Sekalipun di sana ada banyak keterbatasan, namun ini bisa diatasi dengan berusaha untuk <em>qanaah<\/em>, menerima dengan gembira nikmat yang Allah berikan.<\/p>\n<p><em>Allahu a\u2019lam<\/em><\/p>\n<p><strong>Dijawab oleh Ustadz Ammi Nur Baits\u00a0(Dewan Pembina\u00a0Konsultasisyariah.com)<\/strong><\/p>\n<p>Anda bisa membaca artikel ini melalui aplikasi\u00a0<a href=\"https:\/\/play.google.com\/store\/apps\/details?id=org.yufid.tanyaustadz\" target=\"_blank\" rel=\"noopener noreferrer\"><strong>Tanya Ustadz untuk Android<\/strong><\/a>.<br \/>\n<a href=\"https:\/\/play.google.com\/store\/apps\/details?id=org.yufid.tanyaustadz\" target=\"_blank\" rel=\"noopener noreferrer\"><strong>Download Sekarang !!<\/strong><\/a><\/p>\n<p><strong>KonsultasiSyariah.com didukung oleh Zahir Accounting\u00a0<a href=\"http:\/\/zahiraccounting.com\/id\/\" target=\"_blank\" rel=\"noopener noreferrer\">Software Akuntansi Terbaik di Indonesia<\/a>.<\/strong><\/p>\n<p><strong>Dukung Yufid dengan menjadi SPONSOR dan DONATUR.<\/strong><\/p>\n<ul>\n<li>SPONSOR hubungi: 081 326 333 328<\/li>\n<li>DONASI hubungi: 087 882 888 727<\/li>\n<li>Donasi dapat disalurkan ke rekening: 4564807232 (BCA) \/ 7051601496 (Syariah Mandiri) \/ 1370006372474 (Mandiri). a.n. Hendri Syahrial<\/li>\n<\/ul>\n","protected":false},"excerpt":{"rendered":"<p>Haruskah Istri Tinggal Bersama Suami? Saya seorang istri tinggal dijkrt ini sama anak 2 dan cucu . tetapi suami ndak betah disini , mau nya tinggal dkmpung . alasan nya sakit 2 disini .sisuami mintak saya tnggal dikapung . sementara tanggung jawap dan kewajiban nya sebagai suami telah dipikul oleh anak 2 nya .kl mengenai [&hellip;]<\/p>\n","protected":false},"author":7,"featured_media":21821,"comment_status":"closed","ping_status":"open","sticky":false,"template":"","format":"standard","meta":[],"categories":[16],"tags":[16783,20632],"yoast_head":"<!-- This site is optimized with the Yoast SEO plugin v21.7 - https:\/\/yoast.com\/wordpress\/plugins\/seo\/ -->\n<title>Istri Harus Tinggal Bersama Suami? &#8226; KonsultasiSyariah.com<\/title>\n<meta name=\"description\" content=\"Haruskah Istri Tinggal Bersama Suami? Saya seorang istri tinggal dijkrt ini sama anak 2 dan cucu . tetapi suami ndak betah disini , mau nya tinggal\" \/>\n<meta name=\"robots\" content=\"index, follow, max-snippet:-1, max-image-preview:large, max-video-preview:-1\" \/>\n<link rel=\"canonical\" href=\"https:\/\/konsultasisyariah.com\/24361-istri-harus-tinggal-bersama-suami.html\" \/>\n<meta property=\"og:locale\" content=\"en_US\" \/>\n<meta property=\"og:type\" content=\"article\" \/>\n<meta property=\"og:title\" content=\"Istri Harus Tinggal Bersama Suami? &#8226; KonsultasiSyariah.com\" \/>\n<meta property=\"og:description\" content=\"Haruskah Istri Tinggal Bersama Suami? Saya seorang istri tinggal dijkrt ini sama anak 2 dan cucu . tetapi suami ndak betah disini , mau nya tinggal\" \/>\n<meta property=\"og:url\" content=\"https:\/\/konsultasisyariah.com\/24361-istri-harus-tinggal-bersama-suami.html\" \/>\n<meta property=\"og:site_name\" content=\"KonsultasiSyariah.com\" \/>\n<meta property=\"article:publisher\" content=\"https:\/\/www.facebook.com\/KonsultasiSyariah\" \/>\n<meta property=\"article:published_time\" content=\"2015-02-23T06:53:07+00:00\" \/>\n<meta property=\"article:modified_time\" content=\"2021-06-21T10:50:29+00:00\" \/>\n<meta property=\"og:image\" content=\"https:\/\/konsultasisyariah.com\/wp-content\/uploads\/2014\/02\/kriteria-suami-istri.jpg\" \/>\n\t<meta property=\"og:image:width\" content=\"620\" \/>\n\t<meta property=\"og:image:height\" content=\"321\" \/>\n\t<meta property=\"og:image:type\" content=\"image\/jpeg\" \/>\n<meta name=\"author\" content=\"Ammi Nur Baits\" \/>\n<meta name=\"twitter:card\" content=\"summary_large_image\" \/>\n<meta name=\"twitter:label1\" content=\"Written by\" \/>\n\t<meta name=\"twitter:data1\" content=\"Ammi Nur Baits\" \/>\n\t<meta name=\"twitter:label2\" content=\"Est. reading time\" \/>\n\t<meta name=\"twitter:data2\" content=\"2 minutes\" \/>\n<script type=\"application\/ld+json\" class=\"yoast-schema-graph\">{\"@context\":\"https:\/\/schema.org\",\"@graph\":[{\"@type\":\"Article\",\"@id\":\"https:\/\/konsultasisyariah.com\/24361-istri-harus-tinggal-bersama-suami.html#article\",\"isPartOf\":{\"@id\":\"https:\/\/konsultasisyariah.com\/24361-istri-harus-tinggal-bersama-suami.html\"},\"author\":{\"name\":\"Ammi Nur Baits\",\"@id\":\"https:\/\/konsultasisyariah.com\/#\/schema\/person\/77addf943d529186c006a73e6764ef7e\"},\"headline\":\"Istri Harus Tinggal Bersama Suami?\",\"datePublished\":\"2015-02-23T06:53:07+00:00\",\"dateModified\":\"2021-06-21T10:50:29+00:00\",\"mainEntityOfPage\":{\"@id\":\"https:\/\/konsultasisyariah.com\/24361-istri-harus-tinggal-bersama-suami.html\"},\"wordCount\":442,\"publisher\":{\"@id\":\"https:\/\/konsultasisyariah.com\/#organization\"},\"keywords\":[\"suami istri\",\"tinggal dengan suami\"],\"articleSection\":[\"Pernikahan\"],\"inLanguage\":\"en-US\"},{\"@type\":\"WebPage\",\"@id\":\"https:\/\/konsultasisyariah.com\/24361-istri-harus-tinggal-bersama-suami.html\",\"url\":\"https:\/\/konsultasisyariah.com\/24361-istri-harus-tinggal-bersama-suami.html\",\"name\":\"Istri Harus Tinggal Bersama Suami? &#8226; KonsultasiSyariah.com\",\"isPartOf\":{\"@id\":\"https:\/\/konsultasisyariah.com\/#website\"},\"datePublished\":\"2015-02-23T06:53:07+00:00\",\"dateModified\":\"2021-06-21T10:50:29+00:00\",\"description\":\"Haruskah Istri Tinggal Bersama Suami? Saya seorang istri tinggal dijkrt ini sama anak 2 dan cucu . tetapi suami ndak betah disini , mau nya tinggal\",\"breadcrumb\":{\"@id\":\"https:\/\/konsultasisyariah.com\/24361-istri-harus-tinggal-bersama-suami.html#breadcrumb\"},\"inLanguage\":\"en-US\",\"potentialAction\":[{\"@type\":\"ReadAction\",\"target\":[\"https:\/\/konsultasisyariah.com\/24361-istri-harus-tinggal-bersama-suami.html\"]}]},{\"@type\":\"BreadcrumbList\",\"@id\":\"https:\/\/konsultasisyariah.com\/24361-istri-harus-tinggal-bersama-suami.html#breadcrumb\",\"itemListElement\":[{\"@type\":\"ListItem\",\"position\":1,\"name\":\"Konsultasi Syariah\",\"item\":\"https:\/\/konsultasisyariah.com\/\"},{\"@type\":\"ListItem\",\"position\":2,\"name\":\"FIKIH\",\"item\":\"https:\/\/konsultasisyariah.com\/fikih\"},{\"@type\":\"ListItem\",\"position\":3,\"name\":\"Pernikahan\",\"item\":\"https:\/\/konsultasisyariah.com\/fikih\/pernikahan\"},{\"@type\":\"ListItem\",\"position\":4,\"name\":\"Istri Harus Tinggal Bersama Suami?\"}]},{\"@type\":\"WebSite\",\"@id\":\"https:\/\/konsultasisyariah.com\/#website\",\"url\":\"https:\/\/konsultasisyariah.com\/\",\"name\":\"Konsultasi Syariah\",\"description\":\"Konsultasi Agama dan Tanya Jawab Pendidikan Islam\",\"publisher\":{\"@id\":\"https:\/\/konsultasisyariah.com\/#organization\"},\"alternateName\":\"Konsultasi Syariah Islam dan Keluarga\",\"potentialAction\":[{\"@type\":\"SearchAction\",\"target\":{\"@type\":\"EntryPoint\",\"urlTemplate\":\"https:\/\/konsultasisyariah.com\/?s={search_term_string}\"},\"query-input\":\"required name=search_term_string\"}],\"inLanguage\":\"en-US\"},{\"@type\":\"Organization\",\"@id\":\"https:\/\/konsultasisyariah.com\/#organization\",\"name\":\"Yufid.org\",\"url\":\"https:\/\/konsultasisyariah.com\/\",\"logo\":{\"@type\":\"ImageObject\",\"inLanguage\":\"en-US\",\"@id\":\"https:\/\/konsultasisyariah.com\/#\/schema\/logo\/image\/\",\"url\":\"https:\/\/konsultasisyariah.com\/wp-content\/uploads\/2024\/01\/9D8B6204-F59E-4193-8649-5893D409E96C.png\",\"contentUrl\":\"https:\/\/konsultasisyariah.com\/wp-content\/uploads\/2024\/01\/9D8B6204-F59E-4193-8649-5893D409E96C.png\",\"width\":1080,\"height\":1080,\"caption\":\"Yufid.org\"},\"image\":{\"@id\":\"https:\/\/konsultasisyariah.com\/#\/schema\/logo\/image\/\"},\"sameAs\":[\"https:\/\/www.facebook.com\/KonsultasiSyariah\"]},{\"@type\":\"Person\",\"@id\":\"https:\/\/konsultasisyariah.com\/#\/schema\/person\/77addf943d529186c006a73e6764ef7e\",\"name\":\"Ammi Nur Baits\",\"image\":{\"@type\":\"ImageObject\",\"inLanguage\":\"en-US\",\"@id\":\"https:\/\/konsultasisyariah.com\/#\/schema\/person\/image\/\",\"url\":\"https:\/\/secure.gravatar.com\/avatar\/50f7764d7bd203e01f496f19667d6ed9?s=96&d=mm&r=g\",\"contentUrl\":\"https:\/\/secure.gravatar.com\/avatar\/50f7764d7bd203e01f496f19667d6ed9?s=96&d=mm&r=g\",\"caption\":\"Ammi Nur Baits\"},\"description\":\"Ustadz Ammi Nur Baits Beliau adalah Alumni Madinah International University, Jurusan Fiqh dan Ushul Fiqh. Saat ini, beliau aktif sebagai Dewan Pembina website PengusahaMuslim.com, KonsultasiSyariah.com, dan Yufid.TV, serta mengasuh pengajian di beberapa masjid di sekitar kampus UGM.\",\"sameAs\":[\"http:\/\/yufid.org\"]}]}<\/script>\n<!-- \/ Yoast SEO plugin. -->","yoast_head_json":{"title":"Istri Harus Tinggal Bersama Suami? &#8226; KonsultasiSyariah.com","description":"Haruskah Istri Tinggal Bersama Suami? Saya seorang istri tinggal dijkrt ini sama anak 2 dan cucu . tetapi suami ndak betah disini , mau nya tinggal","robots":{"index":"index","follow":"follow","max-snippet":"max-snippet:-1","max-image-preview":"max-image-preview:large","max-video-preview":"max-video-preview:-1"},"canonical":"https:\/\/konsultasisyariah.com\/24361-istri-harus-tinggal-bersama-suami.html","og_locale":"en_US","og_type":"article","og_title":"Istri Harus Tinggal Bersama Suami? &#8226; KonsultasiSyariah.com","og_description":"Haruskah Istri Tinggal Bersama Suami? Saya seorang istri tinggal dijkrt ini sama anak 2 dan cucu . tetapi suami ndak betah disini , mau nya tinggal","og_url":"https:\/\/konsultasisyariah.com\/24361-istri-harus-tinggal-bersama-suami.html","og_site_name":"KonsultasiSyariah.com","article_publisher":"https:\/\/www.facebook.com\/KonsultasiSyariah","article_published_time":"2015-02-23T06:53:07+00:00","article_modified_time":"2021-06-21T10:50:29+00:00","og_image":[{"width":620,"height":321,"url":"https:\/\/konsultasisyariah.com\/wp-content\/uploads\/2014\/02\/kriteria-suami-istri.jpg","type":"image\/jpeg"}],"author":"Ammi Nur Baits","twitter_card":"summary_large_image","twitter_misc":{"Written by":"Ammi Nur Baits","Est. reading time":"2 minutes"},"schema":{"@context":"https:\/\/schema.org","@graph":[{"@type":"Article","@id":"https:\/\/konsultasisyariah.com\/24361-istri-harus-tinggal-bersama-suami.html#article","isPartOf":{"@id":"https:\/\/konsultasisyariah.com\/24361-istri-harus-tinggal-bersama-suami.html"},"author":{"name":"Ammi Nur Baits","@id":"https:\/\/konsultasisyariah.com\/#\/schema\/person\/77addf943d529186c006a73e6764ef7e"},"headline":"Istri Harus Tinggal Bersama Suami?","datePublished":"2015-02-23T06:53:07+00:00","dateModified":"2021-06-21T10:50:29+00:00","mainEntityOfPage":{"@id":"https:\/\/konsultasisyariah.com\/24361-istri-harus-tinggal-bersama-suami.html"},"wordCount":442,"publisher":{"@id":"https:\/\/konsultasisyariah.com\/#organization"},"keywords":["suami istri","tinggal dengan suami"],"articleSection":["Pernikahan"],"inLanguage":"en-US"},{"@type":"WebPage","@id":"https:\/\/konsultasisyariah.com\/24361-istri-harus-tinggal-bersama-suami.html","url":"https:\/\/konsultasisyariah.com\/24361-istri-harus-tinggal-bersama-suami.html","name":"Istri Harus Tinggal Bersama Suami? &#8226; KonsultasiSyariah.com","isPartOf":{"@id":"https:\/\/konsultasisyariah.com\/#website"},"datePublished":"2015-02-23T06:53:07+00:00","dateModified":"2021-06-21T10:50:29+00:00","description":"Haruskah Istri Tinggal Bersama Suami? Saya seorang istri tinggal dijkrt ini sama anak 2 dan cucu . tetapi suami ndak betah disini , mau nya tinggal","breadcrumb":{"@id":"https:\/\/konsultasisyariah.com\/24361-istri-harus-tinggal-bersama-suami.html#breadcrumb"},"inLanguage":"en-US","potentialAction":[{"@type":"ReadAction","target":["https:\/\/konsultasisyariah.com\/24361-istri-harus-tinggal-bersama-suami.html"]}]},{"@type":"BreadcrumbList","@id":"https:\/\/konsultasisyariah.com\/24361-istri-harus-tinggal-bersama-suami.html#breadcrumb","itemListElement":[{"@type":"ListItem","position":1,"name":"Konsultasi Syariah","item":"https:\/\/konsultasisyariah.com\/"},{"@type":"ListItem","position":2,"name":"FIKIH","item":"https:\/\/konsultasisyariah.com\/fikih"},{"@type":"ListItem","position":3,"name":"Pernikahan","item":"https:\/\/konsultasisyariah.com\/fikih\/pernikahan"},{"@type":"ListItem","position":4,"name":"Istri Harus Tinggal Bersama Suami?"}]},{"@type":"WebSite","@id":"https:\/\/konsultasisyariah.com\/#website","url":"https:\/\/konsultasisyariah.com\/","name":"Konsultasi Syariah","description":"Konsultasi Agama dan Tanya Jawab Pendidikan Islam","publisher":{"@id":"https:\/\/konsultasisyariah.com\/#organization"},"alternateName":"Konsultasi Syariah Islam dan Keluarga","potentialAction":[{"@type":"SearchAction","target":{"@type":"EntryPoint","urlTemplate":"https:\/\/konsultasisyariah.com\/?s={search_term_string}"},"query-input":"required name=search_term_string"}],"inLanguage":"en-US"},{"@type":"Organization","@id":"https:\/\/konsultasisyariah.com\/#organization","name":"Yufid.org","url":"https:\/\/konsultasisyariah.com\/","logo":{"@type":"ImageObject","inLanguage":"en-US","@id":"https:\/\/konsultasisyariah.com\/#\/schema\/logo\/image\/","url":"https:\/\/konsultasisyariah.com\/wp-content\/uploads\/2024\/01\/9D8B6204-F59E-4193-8649-5893D409E96C.png","contentUrl":"https:\/\/konsultasisyariah.com\/wp-content\/uploads\/2024\/01\/9D8B6204-F59E-4193-8649-5893D409E96C.png","width":1080,"height":1080,"caption":"Yufid.org"},"image":{"@id":"https:\/\/konsultasisyariah.com\/#\/schema\/logo\/image\/"},"sameAs":["https:\/\/www.facebook.com\/KonsultasiSyariah"]},{"@type":"Person","@id":"https:\/\/konsultasisyariah.com\/#\/schema\/person\/77addf943d529186c006a73e6764ef7e","name":"Ammi Nur Baits","image":{"@type":"ImageObject","inLanguage":"en-US","@id":"https:\/\/konsultasisyariah.com\/#\/schema\/person\/image\/","url":"https:\/\/secure.gravatar.com\/avatar\/50f7764d7bd203e01f496f19667d6ed9?s=96&d=mm&r=g","contentUrl":"https:\/\/secure.gravatar.com\/avatar\/50f7764d7bd203e01f496f19667d6ed9?s=96&d=mm&r=g","caption":"Ammi Nur Baits"},"description":"Ustadz Ammi Nur Baits Beliau adalah Alumni Madinah International University, Jurusan Fiqh dan Ushul Fiqh. Saat ini, beliau aktif sebagai Dewan Pembina website PengusahaMuslim.com, KonsultasiSyariah.com, dan Yufid.TV, serta mengasuh pengajian di beberapa masjid di sekitar kampus UGM.","sameAs":["http:\/\/yufid.org"]}]}},"_links":{"self":[{"href":"https:\/\/konsultasisyariah.com\/wp-json\/wp\/v2\/posts\/24361"}],"collection":[{"href":"https:\/\/konsultasisyariah.com\/wp-json\/wp\/v2\/posts"}],"about":[{"href":"https:\/\/konsultasisyariah.com\/wp-json\/wp\/v2\/types\/post"}],"author":[{"embeddable":true,"href":"https:\/\/konsultasisyariah.com\/wp-json\/wp\/v2\/users\/7"}],"replies":[{"embeddable":true,"href":"https:\/\/konsultasisyariah.com\/wp-json\/wp\/v2\/comments?post=24361"}],"version-history":[{"count":2,"href":"https:\/\/konsultasisyariah.com\/wp-json\/wp\/v2\/posts\/24361\/revisions"}],"predecessor-version":[{"id":37135,"href":"https:\/\/konsultasisyariah.com\/wp-json\/wp\/v2\/posts\/24361\/revisions\/37135"}],"wp:featuredmedia":[{"embeddable":true,"href":"https:\/\/konsultasisyariah.com\/wp-json\/wp\/v2\/media\/21821"}],"wp:attachment":[{"href":"https:\/\/konsultasisyariah.com\/wp-json\/wp\/v2\/media?parent=24361"}],"wp:term":[{"taxonomy":"category","embeddable":true,"href":"https:\/\/konsultasisyariah.com\/wp-json\/wp\/v2\/categories?post=24361"},{"taxonomy":"post_tag","embeddable":true,"href":"https:\/\/konsultasisyariah.com\/wp-json\/wp\/v2\/tags?post=24361"}],"curies":[{"name":"wp","href":"https:\/\/api.w.org\/{rel}","templated":true}]}}