{"id":82599,"date":"2023-02-08T06:00:29","date_gmt":"2023-02-07T23:00:29","guid":{"rendered":"https:\/\/muslim.or.id\/?p=82599"},"modified":"2023-02-08T08:14:51","modified_gmt":"2023-02-08T01:14:51","slug":"dosa-besar-dan-dosa-kecil","status":"publish","type":"post","link":"https:\/\/muslim.or.id\/82599-dosa-besar-dan-dosa-kecil.html","title":{"rendered":"Dosa Besar dan Dosa Kecil"},"content":{"rendered":"<div id=\"ez-toc-container\" class=\"ez-toc-v2_0_65 counter-hierarchy ez-toc-counter ez-toc-transparent ez-toc-container-direction\">\n<div class=\"ez-toc-title-container\">\n<p class=\"ez-toc-title \" >Daftar Isi<\/p>\n<span class=\"ez-toc-title-toggle\"><a href=\"#\" class=\"ez-toc-pull-right ez-toc-btn ez-toc-btn-xs ez-toc-btn-default ez-toc-toggle\" aria-label=\"Toggle Table of Content\"><span class=\"ez-toc-js-icon-con\"><span class=\"\"><span class=\"eztoc-hide\" style=\"display:none;\">Toggle<\/span><span class=\"ez-toc-icon-toggle-span\"><svg style=\"fill: #999;color:#999\" xmlns=\"http:\/\/www.w3.org\/2000\/svg\" class=\"list-377408\" width=\"20px\" height=\"20px\" viewBox=\"0 0 24 24\" fill=\"none\"><path d=\"M6 6H4v2h2V6zm14 0H8v2h12V6zM4 11h2v2H4v-2zm16 0H8v2h12v-2zM4 16h2v2H4v-2zm16 0H8v2h12v-2z\" fill=\"currentColor\"><\/path><\/svg><svg style=\"fill: #999;color:#999\" class=\"arrow-unsorted-368013\" xmlns=\"http:\/\/www.w3.org\/2000\/svg\" width=\"10px\" height=\"10px\" viewBox=\"0 0 24 24\" version=\"1.2\" baseProfile=\"tiny\"><path d=\"M18.2 9.3l-6.2-6.3-6.2 6.3c-.2.2-.3.4-.3.7s.1.5.3.7c.2.2.4.3.7.3h11c.3 0 .5-.1.7-.3.2-.2.3-.5.3-.7s-.1-.5-.3-.7zM5.8 14.7l6.2 6.3 6.2-6.3c.2-.2.3-.5.3-.7s-.1-.5-.3-.7c-.2-.2-.4-.3-.7-.3h-11c-.3 0-.5.1-.7.3-.2.2-.3.5-.3.7s.1.5.3.7z\"\/><\/svg><\/span><\/span><\/span><\/a><\/span><\/div>\n<nav><ul class='ez-toc-list ez-toc-list-level-1 ' ><li class='ez-toc-page-1 ez-toc-heading-level-2'><a class=\"ez-toc-link ez-toc-heading-1\" href=\"#\" data-href=\"https:\/\/muslim.or.id\/82599-dosa-besar-dan-dosa-kecil.html\/#Definisi_dosa\" title=\"Definisi dosa \">Definisi dosa <\/a><\/li><li class='ez-toc-page-1 ez-toc-heading-level-2'><a class=\"ez-toc-link ez-toc-heading-2\" href=\"#\" data-href=\"https:\/\/muslim.or.id\/82599-dosa-besar-dan-dosa-kecil.html\/#Pembagian_dosa_ditinjau_dari_besar_kecilnya\" title=\"Pembagian dosa ditinjau dari besar kecilnya\">Pembagian dosa ditinjau dari besar kecilnya<\/a><ul class='ez-toc-list-level-3' ><li class='ez-toc-heading-level-3'><a class=\"ez-toc-link ez-toc-heading-3\" href=\"#\" data-href=\"https:\/\/muslim.or.id\/82599-dosa-besar-dan-dosa-kecil.html\/#Dosa_besar\" title=\"Dosa besar\">Dosa besar<\/a><\/li><li class='ez-toc-page-1 ez-toc-heading-level-3'><a class=\"ez-toc-link ez-toc-heading-4\" href=\"#\" data-href=\"https:\/\/muslim.or.id\/82599-dosa-besar-dan-dosa-kecil.html\/#Dosa_kecil\" title=\"Dosa kecil\">Dosa kecil<\/a><\/li><\/ul><\/li><\/ul><\/nav><\/div>\n<p style=\"text-align: center;\"><span style=\"font-size: 21pt;\">\u0628\u0650\u0633\u0652\u0645\u0650 \u0627\u0644\u0644\u0647\u0650 \u0627\u0644\u0631\u064e\u0651\u062d\u0652\u0645\u0670\u0646\u0650 \u0627\u0644\u0631\u064e\u0651\u062d\u0650\u064a\u0652\u0645\u0650<\/span><\/p>\n<p><em>Walhamdulillah, wash-shalatu was-salamu &#8216;ala rasulillah. Amma ba&#8217;du,<\/em><\/p>\n<h2><span class=\"ez-toc-section\" id=\"Definisi_dosa\"><\/span><strong>Definisi dosa <\/strong><span class=\"ez-toc-section-end\"><\/span><\/h2>\n<p>Dosa adalah sesuatu yang menyelisihi aturan <em>syar\u2019i<\/em> dengan meninggalkan kewajiban atau melakukan keharaman.<\/p>\n<h2><span class=\"ez-toc-section\" id=\"Pembagian_dosa_ditinjau_dari_besar_kecilnya\"><\/span><strong>Pembagian dosa ditinjau dari besar kecilnya<\/strong><span class=\"ez-toc-section-end\"><\/span><\/h2>\n<p>Ditinjau dari besar kecilnya, dosa terbagi menjadi dua, yaitu:<\/p>\n<h3><span class=\"ez-toc-section\" id=\"Dosa_besar\"><\/span><strong>Dosa besar<\/strong><span class=\"ez-toc-section-end\"><\/span><\/h3>\n<p>Dosa besar adalah dosa yang dalam dalil disebut dengan <strong>hukuman (ancaman) khusus <\/strong>di dunia atau di akhirat, atau disebut sebagai <strong>dosa yang besar.<\/strong><\/p>\n<p>Maksud dari &#8220;hukuman (ancaman) khusus di dunia&#8221;, seperti: hukuman had, atau peniadaan iman, pelakunya disebut fasiq, dan membinasakan di dunia.<\/p>\n<p>Maksud dari &#8220;ancaman (hukuman) khusus di akhirat&#8221;, seperti: neraka, laknat, murka Allah, tidak masuk surga, tidak mencium bau surga, dan membinasakan di akhirat.<\/p>\n<p><strong>Contoh dosa besar: <\/strong><\/p>\n<p>Syirik, sihir, mencela para nabi \u2018<em>alaihimush shalatu wassalam, <\/em>meninggalkan salat wajib 5 waktu, durhaka kepada orang tua, zina, membunuh, minum minuman yang memabukkan, riba, makan harta anak yatim tanpa hak, dll.<\/p>\n<p>Berikut ini kutipan ucapan ulama tentang dosa besar <strong><a href=\"#_ftn1\" name=\"_ftnref1\">[1]<\/a>:<\/strong><\/p>\n<p>Abu Abbas Al-Qurthubi <em>rahimahullah <\/em>berkata,<\/p>\n<p style=\"text-align: center;\"><span style=\"font-size: 21pt;\">\u0627\u0644\u0635\u0651\u064e\u062d\u064a\u062d\u064f \u0625\u0646 \u0634\u0627\u0621 \u0627\u0644\u0644\u0647\u064f \u062a\u0639\u0627\u0644\u0649: \u0623\u0646\u0651\u064e \u0643\u064f\u0644\u0651\u064e \u0630\u064e\u0646\u0628\u064d \u0623\u0637\u0644\u064e\u0642\u064e \u0627\u0644\u0634\u0651\u064e\u0631\u0639\u064f \u0639\u0644\u064a\u0647 \u0623\u0646\u0651\u064e\u0647 \u0643\u0628\u064a\u0631\u064c \u0623\u0648 \u0639\u0638\u064a\u0645\u064c\u060c \u0623\u0648 \u0623\u062e\u0628\u064e\u0631\u064e \u0628\u0634\u0650\u062f\u0651\u064e\u0629\u0650 \u0627\u0644\u0639\u0650\u0642\u0627\u0628\u0650 \u0639\u0644\u064a\u0647\u060c \u0623\u0648 \u0639\u064e\u0644\u0651\u064e\u0642 \u0639\u0644\u064a\u0647 \u062d\u064e\u062f\u0651\u064b\u0627\u060c \u0623\u0648 \u0634\u064e\u062f\u0651\u064e\u062f \u0627\u0644\u0646\u0643\u064a\u0631\u064e \u0639\u0644\u064a\u0647 \u0648\u063a\u064e\u0644\u0651\u064e\u0638\u0647\u060c \u0648\u0634\u064e\u0647\u0650\u062f \u0628\u0630\u0644\u0643 \u0643\u062a\u0627\u0628\u064f \u0627\u0644\u0644\u0647\u0650 \u0623\u0648 \u0633\u064f\u0646\u0651\u064e\u0629\u064c \u0623\u0648 \u0625\u062c\u0645\u0627\u0639\u064c: \u0641\u0647\u0648 \u0643\u0628\u064a\u0631\u0629\u064c<\/span><\/p>\n<p>\u201c<em>Pendapat yang benar insyaAllah Ta\u2019ala bahwa setiap dosa yang dalam syari\u2019at disifati dengan besar (kabir atau \u2018azhim), atau dikabarkan bahwa hukuman bagi pelakunya itu keras, atau disebutkan had (hukuman khusus) bagi pelakunya, atau diingkari dengan keras dan kuat, serta hal tersebut disebutkan dalam Kitabullah, Sunnah, atau ijma\u2019, maka ini adalah dosa besar.<\/em>\u201d<\/p>\n<p>Dan Abu Ya\u2019la <em>rahimahullah<\/em> berkata, \u201cImam Ahmad <em>rahimahullah<\/em> telah mendefinisikan dosa besar dengan definisi,<\/p>\n<p style=\"text-align: center;\"><span style=\"font-size: 21pt;\">\u0628\u0645\u0627 \u064a\u064f\u0648\u062c\u0650\u0628\u064f \u062d\u064e\u062f\u0651\u064b\u0627 \u0641\u064a \u0627\u0644\u062f\u0651\u064f\u0646\u064a\u0627\u060c \u0648\u0648\u0639\u064a\u062f\u064b\u0627 \u0641\u064a \u0627\u0644\u0622\u062e\u0631\u0629\u0650<\/span><\/p>\n<p>\u201c<em>Dosa yang mengakibatkan had (hukuman khusus) di dunia dan diancam (dengan ancaman khusus) di akhirat<\/em>.\u201d<\/p>\n<p>Sedangkan Syaikhul Islam <em>rahimahullah<\/em> menyebutkan bahwa dosa besar adalah dosa yang dihukum (pelakunya) dengan hukuman khusus.<\/p>\n<p><strong>Dalil jenis dosa besar: <\/strong><\/p>\n<p>Di antara dalil-dalil dosa besar adalah firman Allah <em>Ta\u2019ala,<\/em><\/p>\n<p style=\"text-align: center;\"><span style=\"font-size: 21pt;\">\u0627\u064e\u0644\u0651\u064e\u0630\u0650\u064a\u0652\u0646\u064e \u064a\u064e\u062c\u0652\u062a\u064e\u0646\u0650\u0628\u064f\u0648\u0652\u0646\u064e \u0643\u064e\u0628\u0670\u06e4\u0649\u0655\u0650\u0631\u064e \u0627\u0644\u0652\u0627\u0650\u062b\u0652\u0645\u0650 \u0648\u064e\u0627\u0644\u0652\u0641\u064e\u0648\u064e\u0627\u062d\u0650\u0634\u064e \u0627\u0650\u0644\u0651\u064e\u0627 \u0627\u0644\u0644\u0651\u064e\u0645\u064e\u0645\u064e\u06d9 \u0627\u0650\u0646\u0651\u064e \u0631\u064e\u0628\u0651\u064e\u0643\u064e \u0648\u064e\u0627\u0633\u0650\u0639\u064f \u0627\u0644\u0652\u0645\u064e\u063a\u0652\u0641\u0650\u0631\u064e\u0629\u0650\u06d7 \u0647\u064f\u0648\u064e \u0627\u064e\u0639\u0652\u0644\u064e\u0645\u064f \u0628\u0650\u0643\u064f\u0645\u0652 \u0627\u0650\u0630\u0652 \u0627\u064e\u0646\u0652\u0634\u064e\u0627\u064e\u0643\u064f\u0645\u0652 \u0645\u0651\u0650\u0646\u064e \u0627\u0644\u0652\u0627\u064e\u0631\u0652\u0636\u0650 \u0648\u064e\u0627\u0650\u0630\u0652 \u0627\u064e\u0646\u0652\u062a\u064f\u0645\u0652 \u0627\u064e\u062c\u0650\u0646\u0651\u064e\u0629\u064c \u0641\u0650\u064a\u0652 \u0628\u064f\u0637\u064f\u0648\u0652\u0646\u0650 \u0627\u064f\u0645\u0651\u064e\u0647\u0670\u062a\u0650\u0643\u064f\u0645\u0652\u06d7 \u0641\u064e\u0644\u064e\u0627 \u062a\u064f\u0632\u064e\u0643\u0651\u064f\u0648\u0652\u0653\u0627 \u0627\u064e\u0646\u0652\u0641\u064f\u0633\u064e\u0643\u064f\u0645\u0652\u06d7 \u0647\u064f\u0648\u064e \u0627\u064e\u0639\u0652\u0644\u064e\u0645\u064f \u0628\u0650\u0645\u064e\u0646\u0650 \u0627\u062a\u0651\u064e\u0642\u0670\u0649<\/span><\/p>\n<p><em>&#8220;(Yaitu) mereka yang menjauhi <strong>dosa-dosa besar<\/strong> dan perbuatan keji, kecuali <strong>dosa-dosa kecil.<\/strong> Sungguh, Tuhanmu Mahaluas ampunan-Nya. Dia mengetahui tentang kalian, sejak Dia menjadikan kalian dari tanah, lalu ketika kalian masih janin dalam perut ibu kalian. Maka, janganlah kalian menganggap diri suci. Dia mengetahui tentang orang yang bertakwa. <\/em>(QS. An-Najm: 32)<\/p>\n<p>Allah <em>Ta\u2019ala <\/em>berfirman,<\/p>\n<p style=\"text-align: center;\"><span style=\"font-size: 21pt;\">\u0648\u064e\u0648\u064f\u0636\u0650\u0639\u064e \u0627\u0644\u0652\u0643\u0650\u062a\u0670\u0628\u064f \u0641\u064e\u062a\u064e\u0631\u064e\u0649 \u0627\u0644\u0652\u0645\u064f\u062c\u0652\u0631\u0650\u0645\u0650\u064a\u0652\u0646\u064e \u0645\u064f\u0634\u0652\u0641\u0650\u0642\u0650\u064a\u0652\u0646\u064e \u0645\u0650\u0645\u0651\u064e\u0627 \u0641\u0650\u064a\u0652\u0647\u0650 \u0648\u064e\u064a\u064e\u0642\u064f\u0648\u0652\u0644\u064f\u0648\u0652\u0646\u064e \u064a\u0670\u0648\u064e\u064a\u0652\u0644\u064e\u062a\u064e\u0646\u064e\u0627 \u0645\u064e\u0627\u0644\u0650 \u0647\u0670\u0630\u064e\u0627 \u0627\u0644\u0652\u0643\u0650\u062a\u0670\u0628\u0650 \u0644\u064e\u0627 \u064a\u064f\u063a\u064e\u0627\u062f\u0650\u0631\u064f \u0635\u064e\u063a\u0650\u064a\u0652\u0631\u064e\u0629\u064b \u0648\u0651\u064e\u0644\u064e\u0627 \u0643\u064e\u0628\u0650\u064a\u0652\u0631\u064e\u0629\u064b \u0627\u0650\u0644\u0651\u064e\u0627\u0653 \u0627\u064e\u062d\u0652\u0635\u0670\u0649\u0647\u064e\u0627\u06da \u0648\u064e\u0648\u064e\u062c\u064e\u062f\u064f\u0648\u0652\u0627 \u0645\u064e\u0627 \u0639\u064e\u0645\u0650\u0644\u064f\u0648\u0652\u0627 \u062d\u064e\u0627\u0636\u0650\u0631\u064b\u0627\u06d7 \u0648\u064e\u0644\u064e\u0627 \u064a\u064e\u0638\u0652\u0644\u0650\u0645\u064f \u0631\u064e\u0628\u0651\u064f\u0643\u064e \u0627\u064e\u062d\u064e\u062f\u064b\u0627<\/span><\/p>\n<p><em>&#8220;Dan diletakkanlah kitab (catatan amal), lalu engkau akan melihat orang yang berdosa merasa ketakutan terhadap apa yang (tertulis) di dalamnya, dan mereka berkata, &#8216;Betapa celaka kami, kitab apakah ini, tidak ada yang tertinggal <strong>dosa yang kecil maupun dosa yang besar, <\/strong>melainkan tercatat semuanya.&#8217; dan mereka dapati (semua) apa yang telah mereka kerjakan (tertulis). Dan Tuhanmu tidak menzalimi seorang jua pun.&#8221;<\/em> (QS. Al-Kahfi : 49)<\/p>\n<p>Allah <em>Ta\u2019ala<\/em> berfirman,<\/p>\n<p style=\"text-align: center;\"><span style=\"font-size: 21pt;\">\u0648\u064e\u0643\u064f\u0644\u0651\u064f \u0635\u064e\u063a\u0650\u064a\u0652\u0631\u064d \u0648\u0651\u064e\u0643\u064e\u0628\u0650\u064a\u0652\u0631\u064d \u0645\u0651\u064f\u0633\u0652\u062a\u064e\u0637\u064e\u0631\u064c<\/span><\/p>\n<p><em>&#8220;Dan segala <strong>(dosa) yang kecil maupun yang besar<\/strong> (semuanya) tertulis.&#8221;<\/em> (QS. Al-Qomar : 53)<\/p>\n<p>Dari Abu Hurairah<em> radhiyallahu \u2018anhu, <\/em>dari Nabi <em>shallallahu \u2018alaihi wasallam<\/em> bersabda,<\/p>\n<p style=\"text-align: center;\"><span style=\"font-size: 21pt;\">\u0627\u062c\u0652\u062a\u064e\u0646\u0650\u0628\u064f\u0648\u0627 \u0627\u0644\u0633\u0651\u064e\u0628\u0652\u0639\u064e \u0627\u0644\u0652\u0645\u064f\u0648\u0628\u0650\u0642\u064e\u0627\u062a\u0650<\/span><\/p>\n<p>\u201c<em>Jauhilah tujuh perkara yang <strong>membinasakan<\/strong>!<\/em>\u201d<\/p>\n<p>Para sahabat bertanya, \u201cWahai Rasulullah, apakah itu?\u201d<\/p>\n<p>Beliau pun menjawab,<\/p>\n<p style=\"text-align: center;\"><span style=\"font-size: 21pt;\">\u0627\u0644\u0634\u0651\u0650\u0631\u0652\u0643\u064f \u0628\u0650\u0627\u0644\u0644\u0651\u064e\u0647\u0650 \u0648\u064e\u0627\u0644\u0633\u0651\u0650\u062d\u0652\u0631\u064f \u0648\u064e\u0642\u064e\u062a\u0652\u0644\u064f \u0627\u0644\u0646\u0651\u064e\u0641\u0652\u0633\u0650 \u0627\u0644\u0651\u064e\u062a\u0650\u064a \u062d\u064e\u0631\u0651\u064e\u0645\u064e \u0627\u0644\u0644\u0651\u064e\u0647\u064f \u0625\u0650\u0644\u0651\u064e\u0627 \u0628\u0650\u0627\u0644\u0652\u062d\u064e\u0642\u0651\u0650 \u0648\u064e\u0623\u064e\u0643\u0652\u0644\u064f \u0627\u0644\u0631\u0651\u0650\u0628\u064e\u0627 \u0648\u064e\u0623\u064e\u0643\u0652\u0644\u064f \u0645\u064e\u0627\u0644\u0650 \u0627\u0644\u0652\u064a\u064e\u062a\u0650\u064a\u0645\u0650 \u0648\u064e\u0627\u0644\u062a\u0651\u064e\u0648\u064e\u0644\u0651\u0650\u064a \u064a\u064e\u0648\u0652\u0645\u064e \u0627\u0644\u0632\u0651\u064e\u062d\u0652\u0641\u0650 \u0648\u064e\u0642\u064e\u0630\u0652\u0641\u064f \u0627\u0644\u0652\u0645\u064f\u062d\u0652\u0635\u064e\u0646\u064e\u0627\u062a\u0650 \u0627\u0644\u0652\u0645\u064f\u0624\u0652\u0645\u0650\u0646\u064e\u0627\u062a\u0650 \u0627\u0644\u0652\u063a\u064e\u0627\u0641\u0650\u0644\u064e\u0627\u062a\u0650<\/span><\/p>\n<p>\u201c<em>Menyekutukan Allah (syirik), sihir, membunuh manusia yang Allah haramkan kecuali dengan alasan yang hak, makan harta riba, makan harta anak yatim, lari dari medan perang, dan menuduh berzina kepada wanita yang beriman, menjaga kehormatannya, lagi bersih dari perbuatan zina.\u201d <\/em>(HR. Bukhari dan Muslim<em>)<\/em><\/p>\n<p>Dari Abu Bakrah <em>radhiyallahu \u2018anhu<\/em>, Rasulullah <em>shallallahu \u2018alaihi wasallam <\/em>bersabda,<\/p>\n<p style=\"text-align: center;\"><span style=\"font-size: 21pt;\">\u0623\u064e\u0644\u0627 \u0623\u064f\u0646\u064e\u0628\u0651\u0650\u0626\u064f\u0643\u064f\u0645\u0652 \u0628\u0623\u064e\u0643\u0652\u0628\u064e\u0631\u0650 \u0627\u0644\u0643\u064e\u0628\u0627\u0626\u0650\u0631\u0650 \u0642\u064f\u0644\u0652\u0646\u0627: \u0628\u064e\u0644\u064e\u0649 \u064a\u0627 \u0631\u064e\u0633\u0648\u0644\u064e \u0627\u0644\u0644\u0651\u064e\u0647\u0650\u060c \u0642\u0627\u0644\u064e: \u0627\u0644\u0625\u0634\u0652\u0631\u0627\u0643\u064f \u0628\u0627\u0644\u0644\u0651\u064e\u0647\u0650\u060c \u0648\u0639\u064f\u0642\u064f\u0648\u0642\u064f \u0627\u0644\u0648\u0627\u0644\u0650\u062f\u064e\u064a\u0652\u0646\u0650\u060c \u0648\u0643\u0627\u0646\u064e \u0645\u064f\u062a\u0651\u064e\u0643\u0650\u0626\u064b\u0627 \u0641\u064e\u062c\u064e\u0644\u064e\u0633\u064e \u0641\u0642\u0627\u0644\u064e: \u0623\u0644\u0627 \u0648\u0642\u064e\u0648\u0652\u0644\u064f \u0627\u0644\u0632\u0651\u064f\u0648\u0631\u0650\u060c \u0648\u0634\u064e\u0647\u0627\u062f\u064e\u0629\u064f \u0627\u0644\u0632\u0651\u064f\u0648\u0631\u0650\u060c \u0623\u0644\u0627 \u0648\u0642\u064e\u0648\u0652\u0644\u064f \u0627\u0644\u0632\u0651\u064f\u0648\u0631\u0650\u060c \u0648\u0634\u064e\u0647\u0627\u062f\u064e\u0629\u064f \u0627\u0644\u0632\u0651\u064f\u0648\u0631\u0650 \u0641\u064e\u0645\u0627 \u0632\u0627\u0644\u064e \u064a\u0642\u0648\u0644\u064f\u0647\u0627\u060c \u062d\u062a\u0651\u064e\u0649 \u0642\u064f\u0644\u062a\u064f: \u0644\u0627 \u064a\u064e\u0633\u0652\u0643\u064f\u062a\u064f<\/span><\/p>\n<p><em>\u201cMaukah aku beritahukan kepada <strong>kalian dosa terbesar dari dosa-dosa besar?\u201d<\/strong> Kami menjawab, &#8220;Tentu mau, wahai Rasulullah.&#8221; Beliau pun bersabda, &#8220;Menyekutukan Allah, durhaka kepada kedua orangtua.&#8221; Ketika itu beliau sedang bersandar, lalu beliau duduk, melanjutkan sabdanya, \u201cHati-hati dengan perkataan batil dan persaksian batil, hati-hati dengan perkataan batil dan persaksian batil! <\/em><a href=\"#_ftn2\" name=\"_ftnref2\">[2]<\/a><em>\u201d Beliau terus mengulang-ulangi sampai aku bergumam, \u201cWah, beliau tidak berhenti-berhenti.<\/em>\u201d (HR. Bukhari)<\/p>\n<h3><span class=\"ez-toc-section\" id=\"Dosa_kecil\"><\/span><strong>Dosa kecil<\/strong><span class=\"ez-toc-section-end\"><\/span><\/h3>\n<p>Dosa kecil adalah dosa yang dalam dalil<strong> TIDAK ADA <\/strong>hukuman\/ ancaman khusus di dunia atau di akhirat, atau tidak disebut sebagai dosa yang besar.<\/p>\n<p><strong>Contoh dosa kecil <a href=\"#_ftn3\" name=\"_ftnref3\">[3]<\/a>: <\/strong><\/p>\n<p>Menghadapnya seseorang ke arah kiblat saat buang air kecil maupun buang air besar, sedangkan antara dia dengan kiblat tidak ada penghalang yang dekat.<\/p>\n<p>Memotong habis jenggot, ini termasuk dosa kecil, kecuali jika terus menerus melakukannya atau disertai niat <em>tasyabbuh<\/em> dengan wanita atau orang fasiq, maka menjadi dosa besar. Ini adalah pendapat sebagian ulama, sebagaimana difatwakan oleh Syekh Shalih Al-\u2018Ushaimi <em>hafizhahullah <\/em><a href=\"#_ftn4\" name=\"_ftnref4\"><strong>[4]<\/strong><\/a><em>,<\/em> dan fatwa yang mirip dengannya adalah fatwa Syekh Al-Utsaimin <em>rahimahullah <\/em><a href=\"#_ftn5\" name=\"_ftnref5\"><strong>[5]<\/strong><\/a>.<\/p>\n<p><strong>Dalil jenis dosa kecil: <\/strong><\/p>\n<p>Di antara dalil-dalil dosa kecil, selain ketiga dalil di atas, juga:<\/p>\n<p>Dari Abu Ayyub Al-Anshari <em>radhiyallahu \u2018anhu<\/em> bahwa Nabi <em>shallallahu \u2018alaihi wasallam<\/em> bersabda,<\/p>\n<p style=\"text-align: center;\"><span style=\"font-size: 21pt;\">\u0625\u0630\u0627 \u0623\u062a\u064a\u062a\u064f\u0645 \u0627\u0644\u063a\u0627\u0626\u0650\u0637\u064e \u0641\u0644\u0627 \u062a\u0633\u062a\u0642\u0628\u0650\u0644\u0648\u0627 \u0627\u0644\u0642\u0650\u0628\u0644\u0629\u064e\u060c \u0648\u0644\u0627 \u062a\u064e\u0633\u062a\u064e\u062f\u0628\u0650\u0631\u0648\u0647\u0627 \u0628\u0628\u0648\u0644\u064d \u0648\u0644\u0627 \u063a\u0627\u0626\u0650\u0637\u064d\u060c \u0648\u0644\u0643\u0650\u0646 \u0634\u0631\u0651\u0650\u0642\u0648\u0627 \u0623\u0648 \u063a\u064e\u0631\u0651\u0650\u0628\u0648\u0627<\/span><\/p>\n<p>\u201c<em>Jika kalian berada di tempat buang air, maka janganlah menghadap kiblat dan jangan membelakanginya saat buang air kecil maupun buang air besar, tetapi menghadaplah ke timur atau ke barat<\/em>.\u201d (HR. Bukhari dan Muslim)<\/p>\n<p>Dalam riwayat Imam Muslim dari Abu Hurairah <em>radhiyallahu \u2018anhu, <\/em>dari Rasulullah <em>shallallahu \u2018alaihi wasallam<\/em>,<\/p>\n<p style=\"text-align: center;\"><span style=\"font-size: 21pt;\">\u062c\u0632\u0648\u0627 \u0627\u0644\u0634\u0648\u0627\u0631\u0628\u060c \u0648\u0627\u0639\u0641\u0648\u0627 \u0627\u0644\u0644\u062d\u0649\u060c \u062e\u0627\u0644\u0641\u0648\u0627 \u0627\u0644\u0645\u062c\u0648\u0633<\/span><\/p>\n<p>\u201c<em>Cukurlah kumis, panjangkanlah jenggot, dan selisihilah orang-orang majusi<\/em>.\u201d<\/p>\n<p>Dalam hadis Aisyah yang diriwayatkan oleh Imam Muslim dan dari selain beliau, bahwa Rasulullah <em>shallallahu \u2018alaihi wasallam<\/em> bersabda,<\/p>\n<p style=\"text-align: center;\"><span style=\"font-size: 21pt;\">\u0639\u064e\u0634\u0652\u0631\u064c \u0645\u0650\u0646\u064e \u0627\u0644\u0652\u0641\u0650\u0637\u0652\u0631\u064e\u0629\u0650 \u0642\u064e\u0635\u0651\u064f \u0627\u0644\u0634\u0651\u064e\u0627\u0631\u0650\u0628\u0650 \u0648\u064e\u0625\u0650\u0639\u0652\u0641\u064e\u0627\u0621\u064f \u0627\u0644\u0644\u0651\u0650\u062d\u0652\u064a\u064e\u0629\u0650<\/span><\/p>\n<p>\u201c<em>Sepuluh hal yang termasuk fitrah, yaitu mencukur kumis dan memanjangkan jenggot.<\/em>\u201d<\/p>\n<p><em>Wallahu a\u2019lam<\/em><\/p>\n<p style=\"text-align: center;\"><span style=\"font-size: 21pt;\">\u0627\u0644\u062d\u0645\u062f \u0644\u0650\u0644\u064e\u0651\u0647\u0650 \u0627\u0644\u064e\u0651\u0630\u0650\u064a \u0628\u0650\u0646\u0650\u0639\u0652\u0645\u064e\u062a\u0650\u0647\u0650 \u062a\u064e\u062a\u0650\u0645\u064f\u0651 \u0627\u0644\u0635\u064e\u0651\u0627\u0644\u0650\u062d\u064e\u0627\u062a\u064f<\/span><\/p>\n<p>&nbsp;<\/p>\n<p><strong>BACA JUGA:<\/strong><\/p>\n<p><strong>***<\/strong><\/p>\n<ul>\n<li class=\"jeg_post_title\"><strong><a href=\"https:\/\/muslim.or.id\/82364-mencela-dosa-orang-lain.html\">Fatwa: Hadis tentang Mencela Dosa Orang Lain<\/a><\/strong><\/li>\n<li class=\"jeg_post_title\"><a href=\"https:\/\/muslim.or.id\/81714-tidak-membayar-zakat-adalah-dosa-besar.html\"><strong>Tidak Membayar Zakat adalah Dosa Besar<\/strong><\/a><\/li>\n<\/ul>\n<p>&nbsp;<\/p>\n<p><strong>Penulis: <span style=\"color: #ff0000;\" data-darkreader-inline-color=\"\">Sa&#8217;id Abu Ukkasyah<\/span><\/strong><\/p>\n<p><strong>Artikel: <span style=\"color: #ff0000;\" data-darkreader-inline-color=\"\">www.muslim.or.id<\/span><\/strong><\/p>\n<p>&nbsp;<\/p>\n<p><strong>Catatan kaki:<\/strong><\/p>\n<p><span style=\"color: #000000;\" data-darkreader-inline-color=\"\"><strong><a style=\"color: #000000;\" href=\"#_ftnref1\" name=\"_ftn1\" data-darkreader-inline-color=\"\">[1]<\/a><\/strong> <a style=\"color: #000000;\" href=\"https:\/\/dorar.net\/aqeeda\/2646\" data-darkreader-inline-color=\"\"><strong>https:\/\/dorar.net\/aqeeda\/2646<\/strong><\/a><\/span><\/p>\n<p><strong><span style=\"color: #000000;\" data-darkreader-inline-color=\"\"><a style=\"color: #000000;\" href=\"#_ftnref2\" name=\"_ftn2\" data-darkreader-inline-color=\"\">[2]<\/a><\/span> <\/strong>Seluruh perkataan batil, baik ucapan dusta, persaksian palsu, maupun selainnya.<\/p>\n<p><span style=\"color: #000000;\" data-darkreader-inline-color=\"\"><strong><a style=\"color: #000000;\" href=\"#_ftnref3\" name=\"_ftn3\" data-darkreader-inline-color=\"\">[3]<\/a><\/strong><\/span> shorturl.at\/hxCDI<\/p>\n<p><strong><span style=\"color: #000000;\" data-darkreader-inline-color=\"\"><a style=\"color: #000000;\" href=\"#_ftnref4\" name=\"_ftn4\" data-darkreader-inline-color=\"\">[4]<\/a><\/span> <span style=\"color: #000000;\" data-darkreader-inline-color=\"\"><a style=\"color: #000000;\" href=\"https:\/\/www.youtube.com\/watch?v=QjvMlUb5zvQ\" data-darkreader-inline-color=\"\">https:\/\/www.youtube.com\/watch?v=QjvMlUb5zvQ<\/a><\/span><\/strong><\/p>\n<p><span style=\"color: #000000;\" data-darkreader-inline-color=\"\"><strong><a style=\"color: #000000;\" href=\"#_ftnref5\" name=\"_ftn5\" data-darkreader-inline-color=\"\">[5]<\/a><\/strong> <strong><a style=\"color: #000000;\" href=\"https:\/\/shamela.ws\/book\/2300\/1358\" data-darkreader-inline-color=\"\">https:\/\/shamela.ws\/book\/2300\/1358<\/a><\/strong><\/span><\/p>\n","protected":false},"excerpt":{"rendered":"<p>\u0628\u0650\u0633\u0652\u0645\u0650 \u0627\u0644\u0644\u0647\u0650 \u0627\u0644\u0631\u064e\u0651\u062d\u0652\u0645\u0670\u0646\u0650 \u0627\u0644\u0631\u064e\u0651\u062d\u0650\u064a\u0652\u0645\u0650 Walhamdulillah, wash-shalatu was-salamu &#8216;ala rasulillah. Amma ba&#8217;du, Definisi dosa Dosa adalah sesuatu yang menyelisihi aturan syar\u2019i dengan meninggalkan kewajiban atau melakukan keharaman. Pembagian dosa ditinjau dari besar kecilnya Ditinjau dari besar kecilnya, dosa terbagi menjadi dua, yaitu: Dosa besar Dosa besar adalah dosa yang dalam dalil disebut dengan hukuman (ancaman) khusus [&hellip;]<\/p>\n","protected":false},"author":118,"featured_media":82678,"comment_status":"open","ping_status":"closed","sticky":false,"template":"","format":"standard","meta":{"_monsterinsights_skip_tracking":false,"_monsterinsights_sitenote_active":false,"_monsterinsights_sitenote_note":"","_monsterinsights_sitenote_category":0,"footnotes":""},"categories":[3],"tags":[2768,4266,8918,362,1124,2834,5097],"yoast_head":"<!-- This site is optimized with the Yoast SEO plugin v22.6 - https:\/\/yoast.com\/wordpress\/plugins\/seo\/ -->\n<title>Dosa Besar dan Dosa Kecil<\/title>\n<meta name=\"description\" content=\"Walhamdulillah, wash-shalatu was-salamu &#039;ala rasulillah. Amma ba&#039;du,\" \/>\n<meta name=\"robots\" content=\"index, follow, max-snippet:-1, max-image-preview:large, max-video-preview:-1\" \/>\n<link rel=\"canonical\" href=\"https:\/\/muslim.or.id\/82599-dosa-besar-dan-dosa-kecil.html\" \/>\n<meta property=\"og:locale\" content=\"id_ID\" \/>\n<meta property=\"og:type\" content=\"article\" \/>\n<meta property=\"og:title\" content=\"Dosa Besar dan Dosa Kecil\" \/>\n<meta property=\"og:description\" content=\"Walhamdulillah, wash-shalatu was-salamu &#039;ala rasulillah. Amma ba&#039;du,\" \/>\n<meta property=\"og:url\" content=\"https:\/\/muslim.or.id\/82599-dosa-besar-dan-dosa-kecil.html\" \/>\n<meta property=\"og:site_name\" content=\"Muslim.or.id\" \/>\n<meta property=\"article:publisher\" content=\"https:\/\/www.facebook.com\/muslim.or.id\" \/>\n<meta property=\"article:author\" content=\"https:\/\/www.facebook.com\/au.said.5\" \/>\n<meta property=\"article:published_time\" content=\"2023-02-07T23:00:29+00:00\" \/>\n<meta property=\"article:modified_time\" content=\"2023-02-08T01:14:51+00:00\" \/>\n<meta property=\"og:image\" content=\"http:\/\/muslim.or.id\/wp-content\/uploads\/2023\/02\/20230208-Dosa-Besar-dan-Dosa-Kecil.webp\" \/>\n\t<meta property=\"og:image:width\" content=\"810\" \/>\n\t<meta property=\"og:image:height\" content=\"500\" \/>\n\t<meta property=\"og:image:type\" content=\"image\/webp\" \/>\n<meta name=\"author\" content=\"Sa&#039;id Abu Ukkasyah\" \/>\n<meta name=\"twitter:card\" content=\"summary_large_image\" \/>\n<meta name=\"twitter:creator\" content=\"@muslimorid\" \/>\n<meta name=\"twitter:site\" content=\"@muslimorid\" \/>\n<meta name=\"twitter:label1\" content=\"Ditulis oleh\" \/>\n\t<meta name=\"twitter:data1\" content=\"Sa'id Abu Ukkasyah\" \/>\n\t<meta name=\"twitter:label2\" content=\"Estimasi waktu membaca\" \/>\n\t<meta name=\"twitter:data2\" content=\"4 menit\" \/>\n<script type=\"application\/ld+json\" class=\"yoast-schema-graph\">{\"@context\":\"https:\/\/schema.org\",\"@graph\":[{\"@type\":\"Article\",\"@id\":\"https:\/\/muslim.or.id\/82599-dosa-besar-dan-dosa-kecil.html#article\",\"isPartOf\":{\"@id\":\"https:\/\/muslim.or.id\/82599-dosa-besar-dan-dosa-kecil.html\"},\"author\":{\"name\":\"Sa'id Abu Ukkasyah\",\"@id\":\"https:\/\/muslim.or.id\/#\/schema\/person\/f3d594af1d467a0ef84e317f6d7ca617\"},\"headline\":\"Dosa Besar dan Dosa Kecil\",\"datePublished\":\"2023-02-07T23:00:29+00:00\",\"dateModified\":\"2023-02-08T01:14:51+00:00\",\"mainEntityOfPage\":{\"@id\":\"https:\/\/muslim.or.id\/82599-dosa-besar-dan-dosa-kecil.html\"},\"wordCount\":815,\"commentCount\":0,\"publisher\":{\"@id\":\"https:\/\/muslim.or.id\/#organization\"},\"image\":{\"@id\":\"https:\/\/muslim.or.id\/82599-dosa-besar-dan-dosa-kecil.html#primaryimage\"},\"thumbnailUrl\":\"https:\/\/cdnm.muslim.or.id\/wp-content\/uploads\/2023\/02\/20230208-Dosa-Besar-dan-Dosa-Kecil.webp?strip=all&lossy=1&ssl=1\",\"keywords\":[\"Abdurrazaq bin Abdil Muhsin Al Abbad\",\"akibat dosa\",\"akibat dosa besar\",\"dosa\",\"dosa besar\",\"dosa kecil\",\"dosa maksiat\"],\"articleSection\":[\"Akhlak dan Nasihat\"],\"inLanguage\":\"id\",\"potentialAction\":[{\"@type\":\"CommentAction\",\"name\":\"Comment\",\"target\":[\"https:\/\/muslim.or.id\/82599-dosa-besar-dan-dosa-kecil.html#respond\"]}]},{\"@type\":\"WebPage\",\"@id\":\"https:\/\/muslim.or.id\/82599-dosa-besar-dan-dosa-kecil.html\",\"url\":\"https:\/\/muslim.or.id\/82599-dosa-besar-dan-dosa-kecil.html\",\"name\":\"Dosa Besar dan Dosa Kecil\",\"isPartOf\":{\"@id\":\"https:\/\/muslim.or.id\/#website\"},\"primaryImageOfPage\":{\"@id\":\"https:\/\/muslim.or.id\/82599-dosa-besar-dan-dosa-kecil.html#primaryimage\"},\"image\":{\"@id\":\"https:\/\/muslim.or.id\/82599-dosa-besar-dan-dosa-kecil.html#primaryimage\"},\"thumbnailUrl\":\"https:\/\/cdnm.muslim.or.id\/wp-content\/uploads\/2023\/02\/20230208-Dosa-Besar-dan-Dosa-Kecil.webp?strip=all&lossy=1&ssl=1\",\"datePublished\":\"2023-02-07T23:00:29+00:00\",\"dateModified\":\"2023-02-08T01:14:51+00:00\",\"description\":\"Walhamdulillah, wash-shalatu was-salamu 'ala rasulillah. Amma ba'du,\",\"breadcrumb\":{\"@id\":\"https:\/\/muslim.or.id\/82599-dosa-besar-dan-dosa-kecil.html#breadcrumb\"},\"inLanguage\":\"id\",\"potentialAction\":[{\"@type\":\"ReadAction\",\"target\":[\"https:\/\/muslim.or.id\/82599-dosa-besar-dan-dosa-kecil.html\"]}]},{\"@type\":\"ImageObject\",\"inLanguage\":\"id\",\"@id\":\"https:\/\/muslim.or.id\/82599-dosa-besar-dan-dosa-kecil.html#primaryimage\",\"url\":\"https:\/\/cdnm.muslim.or.id\/wp-content\/uploads\/2023\/02\/20230208-Dosa-Besar-dan-Dosa-Kecil.webp?strip=all&lossy=1&ssl=1\",\"contentUrl\":\"https:\/\/cdnm.muslim.or.id\/wp-content\/uploads\/2023\/02\/20230208-Dosa-Besar-dan-Dosa-Kecil.webp?strip=all&lossy=1&ssl=1\",\"width\":810,\"height\":500,\"caption\":\"dosa besar dosa kecil\"},{\"@type\":\"BreadcrumbList\",\"@id\":\"https:\/\/muslim.or.id\/82599-dosa-besar-dan-dosa-kecil.html#breadcrumb\",\"itemListElement\":[{\"@type\":\"ListItem\",\"position\":1,\"name\":\"Beranda\",\"item\":\"https:\/\/muslim.or.id\/\"},{\"@type\":\"ListItem\",\"position\":2,\"name\":\"Akhlak dan Nasihat\",\"item\":\"https:\/\/muslim.or.id\/category\/akhlak-dan-nasihat\"},{\"@type\":\"ListItem\",\"position\":3,\"name\":\"Dosa Besar dan Dosa Kecil\"}]},{\"@type\":\"WebSite\",\"@id\":\"https:\/\/muslim.or.id\/#website\",\"url\":\"https:\/\/muslim.or.id\/\",\"name\":\"Muslim.or.id\",\"description\":\"Memurnikan Aqidah Menebarkan Sunnah\",\"publisher\":{\"@id\":\"https:\/\/muslim.or.id\/#organization\"},\"potentialAction\":[{\"@type\":\"SearchAction\",\"target\":{\"@type\":\"EntryPoint\",\"urlTemplate\":\"https:\/\/muslim.or.id\/?s={search_term_string}\"},\"query-input\":\"required name=search_term_string\"}],\"inLanguage\":\"id\"},{\"@type\":\"Organization\",\"@id\":\"https:\/\/muslim.or.id\/#organization\",\"name\":\"Muslim.or.id\",\"url\":\"https:\/\/muslim.or.id\/\",\"logo\":{\"@type\":\"ImageObject\",\"inLanguage\":\"id\",\"@id\":\"https:\/\/muslim.or.id\/#\/schema\/logo\/image\/\",\"url\":\"\",\"contentUrl\":\"\",\"caption\":\"Muslim.or.id\"},\"image\":{\"@id\":\"https:\/\/muslim.or.id\/#\/schema\/logo\/image\/\"},\"sameAs\":[\"https:\/\/www.facebook.com\/muslim.or.id\",\"https:\/\/x.com\/muslimorid\",\"https:\/\/instagram.com\/muslimorid\",\"https:\/\/www.pinterest.com\/muslimorid\",\"https:\/\/youtube.com\/muslimorid\"]},{\"@type\":\"Person\",\"@id\":\"https:\/\/muslim.or.id\/#\/schema\/person\/f3d594af1d467a0ef84e317f6d7ca617\",\"name\":\"Sa'id Abu Ukkasyah\",\"image\":{\"@type\":\"ImageObject\",\"inLanguage\":\"id\",\"@id\":\"https:\/\/muslim.or.id\/#\/schema\/person\/image\/\",\"url\":\"https:\/\/secure.gravatar.com\/avatar\/8c48445ebbde24b654400f7cfcdd0119?s=96&d=mm&r=g\",\"contentUrl\":\"https:\/\/secure.gravatar.com\/avatar\/8c48445ebbde24b654400f7cfcdd0119?s=96&d=mm&r=g\",\"caption\":\"Sa'id Abu Ukkasyah\"},\"description\":\"Pengajar Ma'had Jamilurrahman As Salafy Yogyakarta (hingga 1436H), Pengajar Ma'had Al Ilmi Yogyakarta, Pengajar Islamic Center Baitul Muhsinin (ICBM) Medari Yogyakarta\",\"sameAs\":[\"https:\/\/www.facebook.com\/au.said.5\"],\"url\":\"https:\/\/muslim.or.id\/author\/abu-ukkasyah\"}]}<\/script>\n<!-- \/ Yoast SEO plugin. -->","yoast_head_json":{"title":"Dosa Besar dan Dosa Kecil","description":"Walhamdulillah, wash-shalatu was-salamu 'ala rasulillah. Amma ba'du,","robots":{"index":"index","follow":"follow","max-snippet":"max-snippet:-1","max-image-preview":"max-image-preview:large","max-video-preview":"max-video-preview:-1"},"canonical":"https:\/\/muslim.or.id\/82599-dosa-besar-dan-dosa-kecil.html","og_locale":"id_ID","og_type":"article","og_title":"Dosa Besar dan Dosa Kecil","og_description":"Walhamdulillah, wash-shalatu was-salamu 'ala rasulillah. Amma ba'du,","og_url":"https:\/\/muslim.or.id\/82599-dosa-besar-dan-dosa-kecil.html","og_site_name":"Muslim.or.id","article_publisher":"https:\/\/www.facebook.com\/muslim.or.id","article_author":"https:\/\/www.facebook.com\/au.said.5","article_published_time":"2023-02-07T23:00:29+00:00","article_modified_time":"2023-02-08T01:14:51+00:00","og_image":[{"width":810,"height":500,"url":"http:\/\/muslim.or.id\/wp-content\/uploads\/2023\/02\/20230208-Dosa-Besar-dan-Dosa-Kecil.webp","type":"image\/webp"}],"author":"Sa'id Abu Ukkasyah","twitter_card":"summary_large_image","twitter_creator":"@muslimorid","twitter_site":"@muslimorid","twitter_misc":{"Ditulis oleh":"Sa'id Abu Ukkasyah","Estimasi waktu membaca":"4 menit"},"schema":{"@context":"https:\/\/schema.org","@graph":[{"@type":"Article","@id":"https:\/\/muslim.or.id\/82599-dosa-besar-dan-dosa-kecil.html#article","isPartOf":{"@id":"https:\/\/muslim.or.id\/82599-dosa-besar-dan-dosa-kecil.html"},"author":{"name":"Sa'id Abu Ukkasyah","@id":"https:\/\/muslim.or.id\/#\/schema\/person\/f3d594af1d467a0ef84e317f6d7ca617"},"headline":"Dosa Besar dan Dosa Kecil","datePublished":"2023-02-07T23:00:29+00:00","dateModified":"2023-02-08T01:14:51+00:00","mainEntityOfPage":{"@id":"https:\/\/muslim.or.id\/82599-dosa-besar-dan-dosa-kecil.html"},"wordCount":815,"commentCount":0,"publisher":{"@id":"https:\/\/muslim.or.id\/#organization"},"image":{"@id":"https:\/\/muslim.or.id\/82599-dosa-besar-dan-dosa-kecil.html#primaryimage"},"thumbnailUrl":"https:\/\/cdnm.muslim.or.id\/wp-content\/uploads\/2023\/02\/20230208-Dosa-Besar-dan-Dosa-Kecil.webp?strip=all&lossy=1&ssl=1","keywords":["Abdurrazaq bin Abdil Muhsin Al Abbad","akibat dosa","akibat dosa besar","dosa","dosa besar","dosa kecil","dosa maksiat"],"articleSection":["Akhlak dan Nasihat"],"inLanguage":"id","potentialAction":[{"@type":"CommentAction","name":"Comment","target":["https:\/\/muslim.or.id\/82599-dosa-besar-dan-dosa-kecil.html#respond"]}]},{"@type":"WebPage","@id":"https:\/\/muslim.or.id\/82599-dosa-besar-dan-dosa-kecil.html","url":"https:\/\/muslim.or.id\/82599-dosa-besar-dan-dosa-kecil.html","name":"Dosa Besar dan Dosa Kecil","isPartOf":{"@id":"https:\/\/muslim.or.id\/#website"},"primaryImageOfPage":{"@id":"https:\/\/muslim.or.id\/82599-dosa-besar-dan-dosa-kecil.html#primaryimage"},"image":{"@id":"https:\/\/muslim.or.id\/82599-dosa-besar-dan-dosa-kecil.html#primaryimage"},"thumbnailUrl":"https:\/\/cdnm.muslim.or.id\/wp-content\/uploads\/2023\/02\/20230208-Dosa-Besar-dan-Dosa-Kecil.webp?strip=all&lossy=1&ssl=1","datePublished":"2023-02-07T23:00:29+00:00","dateModified":"2023-02-08T01:14:51+00:00","description":"Walhamdulillah, wash-shalatu was-salamu 'ala rasulillah. Amma ba'du,","breadcrumb":{"@id":"https:\/\/muslim.or.id\/82599-dosa-besar-dan-dosa-kecil.html#breadcrumb"},"inLanguage":"id","potentialAction":[{"@type":"ReadAction","target":["https:\/\/muslim.or.id\/82599-dosa-besar-dan-dosa-kecil.html"]}]},{"@type":"ImageObject","inLanguage":"id","@id":"https:\/\/muslim.or.id\/82599-dosa-besar-dan-dosa-kecil.html#primaryimage","url":"https:\/\/cdnm.muslim.or.id\/wp-content\/uploads\/2023\/02\/20230208-Dosa-Besar-dan-Dosa-Kecil.webp?strip=all&lossy=1&ssl=1","contentUrl":"https:\/\/cdnm.muslim.or.id\/wp-content\/uploads\/2023\/02\/20230208-Dosa-Besar-dan-Dosa-Kecil.webp?strip=all&lossy=1&ssl=1","width":810,"height":500,"caption":"dosa besar dosa kecil"},{"@type":"BreadcrumbList","@id":"https:\/\/muslim.or.id\/82599-dosa-besar-dan-dosa-kecil.html#breadcrumb","itemListElement":[{"@type":"ListItem","position":1,"name":"Beranda","item":"https:\/\/muslim.or.id\/"},{"@type":"ListItem","position":2,"name":"Akhlak dan Nasihat","item":"https:\/\/muslim.or.id\/category\/akhlak-dan-nasihat"},{"@type":"ListItem","position":3,"name":"Dosa Besar dan Dosa Kecil"}]},{"@type":"WebSite","@id":"https:\/\/muslim.or.id\/#website","url":"https:\/\/muslim.or.id\/","name":"Muslim.or.id","description":"Memurnikan Aqidah Menebarkan Sunnah","publisher":{"@id":"https:\/\/muslim.or.id\/#organization"},"potentialAction":[{"@type":"SearchAction","target":{"@type":"EntryPoint","urlTemplate":"https:\/\/muslim.or.id\/?s={search_term_string}"},"query-input":"required name=search_term_string"}],"inLanguage":"id"},{"@type":"Organization","@id":"https:\/\/muslim.or.id\/#organization","name":"Muslim.or.id","url":"https:\/\/muslim.or.id\/","logo":{"@type":"ImageObject","inLanguage":"id","@id":"https:\/\/muslim.or.id\/#\/schema\/logo\/image\/","url":"","contentUrl":"","caption":"Muslim.or.id"},"image":{"@id":"https:\/\/muslim.or.id\/#\/schema\/logo\/image\/"},"sameAs":["https:\/\/www.facebook.com\/muslim.or.id","https:\/\/x.com\/muslimorid","https:\/\/instagram.com\/muslimorid","https:\/\/www.pinterest.com\/muslimorid","https:\/\/youtube.com\/muslimorid"]},{"@type":"Person","@id":"https:\/\/muslim.or.id\/#\/schema\/person\/f3d594af1d467a0ef84e317f6d7ca617","name":"Sa'id Abu Ukkasyah","image":{"@type":"ImageObject","inLanguage":"id","@id":"https:\/\/muslim.or.id\/#\/schema\/person\/image\/","url":"https:\/\/secure.gravatar.com\/avatar\/8c48445ebbde24b654400f7cfcdd0119?s=96&d=mm&r=g","contentUrl":"https:\/\/secure.gravatar.com\/avatar\/8c48445ebbde24b654400f7cfcdd0119?s=96&d=mm&r=g","caption":"Sa'id Abu Ukkasyah"},"description":"Pengajar Ma'had Jamilurrahman As Salafy Yogyakarta (hingga 1436H), Pengajar Ma'had Al Ilmi Yogyakarta, Pengajar Islamic Center Baitul Muhsinin (ICBM) Medari Yogyakarta","sameAs":["https:\/\/www.facebook.com\/au.said.5"],"url":"https:\/\/muslim.or.id\/author\/abu-ukkasyah"}]}},"_links":{"self":[{"href":"https:\/\/muslim.or.id\/wp-json\/wp\/v2\/posts\/82599"}],"collection":[{"href":"https:\/\/muslim.or.id\/wp-json\/wp\/v2\/posts"}],"about":[{"href":"https:\/\/muslim.or.id\/wp-json\/wp\/v2\/types\/post"}],"author":[{"embeddable":true,"href":"https:\/\/muslim.or.id\/wp-json\/wp\/v2\/users\/118"}],"replies":[{"embeddable":true,"href":"https:\/\/muslim.or.id\/wp-json\/wp\/v2\/comments?post=82599"}],"version-history":[{"count":0,"href":"https:\/\/muslim.or.id\/wp-json\/wp\/v2\/posts\/82599\/revisions"}],"wp:featuredmedia":[{"embeddable":true,"href":"https:\/\/muslim.or.id\/wp-json\/wp\/v2\/media\/82678"}],"wp:attachment":[{"href":"https:\/\/muslim.or.id\/wp-json\/wp\/v2\/media?parent=82599"}],"wp:term":[{"taxonomy":"category","embeddable":true,"href":"https:\/\/muslim.or.id\/wp-json\/wp\/v2\/categories?post=82599"},{"taxonomy":"post_tag","embeddable":true,"href":"https:\/\/muslim.or.id\/wp-json\/wp\/v2\/tags?post=82599"}],"curies":[{"name":"wp","href":"https:\/\/api.w.org\/{rel}","templated":true}]}}